uitl_dragonfly_sdk/DragonflyClient.py
uitl_dragonfly_sdk/__init__.py
uitl_dragonfly_sdk/__main__.py
uitl_dragonfly_sdk/common/DragonflyException.py
uitl_dragonfly_sdk/common/LowDcrException.py
uitl_dragonfly_sdk/common/__init__.py
uitl_dragonfly_sdk/common/util.py
uitl_dragonfly_sdk-0.1.1.dist-info/LICENSE
uitl_dragonfly_sdk-0.1.1.dist-info/METADATA
uitl_dragonfly_sdk-0.1.1.dist-info/WHEEL
uitl_dragonfly_sdk-0.1.1.dist-info/RECORD
