Metadata-Version: 2.1
Name: uitl-dragonfly-sdk
Version: 0.1.1
Summary: Health check execution SDK for 'Dragonfly, The Data Quality Monitoring Tool' from Upshot Ideas Technology Lab.
License: MIT
Author: NikhilWanpal
Author-email: hello@upshotideas.com
Requires-Python: >=3.8,<4.0
Classifier: License :: OSI Approved :: MIT License
Classifier: Programming Language :: Python :: 3
Classifier: Programming Language :: Python :: 3.8
Classifier: Programming Language :: Python :: 3.9
Classifier: Programming Language :: Python :: 3.10
Classifier: Programming Language :: Python :: 3.11
Classifier: Programming Language :: Python :: 3.12
Requires-Dist: requests (==2.32.3)
